<?xml version="1.0"?>
<!-- edited with XMLSpy v2020 (x64) (http://www.altova.com) by Andrew Auseon (Private) -->
<Root>
	<Entry>
		<zType>SUBJECT_HIGH_FAME</zType>
		<Class>SUBJECTCLASS_CHARACTER</Class>
		<aiMinRating>
			<Pair>
				<zIndex>RATING_FAME</zIndex>
				<iValue>2</iValue>
			</Pair>
		</aiMinRating>
	</Entry>
	<Entry>
		<zType>SUBJECT_LOW_FAME</zType>
		<Class>SUBJECTCLASS_CHARACTER</Class>
		<aiMaxRating>
			<Pair>
				<zIndex>RATING_FAME</zIndex>
				<iValue>-2</iValue>
			</Pair>
		</aiMaxRating>
	</Entry>
	<Entry>
		<zType>SUBJECT_STUDY_ASTRONOMY</zType>
		<Class>SUBJECTCLASS_CHARACTER</Class>
		<TraitPrereq>TRAIT_STUDY_ASTRONOMY</TraitPrereq>
	</Entry>
	<Entry>
		<zType>SUBJECT_STUDY_PYTHAGOREANISM</zType>
		<Class>SUBJECTCLASS_CHARACTER</Class>
		<TraitPrereq>TRAIT_STUDY_PYTHAGOREANISM</TraitPrereq>
	</Entry>
	<Entry>
		<zType>SUBJECT_STUDY_ANY</zType>
		<Class>SUBJECTCLASS_CHARACTER</Class>
		<aeTraitAny>
			<zValue>TRAIT_STUDY_ASTRONOMY</zValue>
			<zValue>TRAIT_STUDY_PYTHAGOREANISM</zValue>
		</aeTraitAny>
	</Entry>
	<Entry>
		<zType>SUBJECT_PLAYER_SKYEXPLORER</zType>
		<Class>SUBJECTCLASS_PLAYER</Class>
		<TraitPrereq>TRAIT_SKYEXPLORER_ARCHETYPE</TraitPrereq>
		<aiMinRating>
			<Pair>
				<zIndex>RATING_WISDOM</zIndex>
				<iValue>2</iValue>
			</Pair>
		</aiMinRating>
	</Entry>
	<Entry>
		<zType>SUBJECT_PLAYER_CORRUPTIONIST</zType>
		<Class>SUBJECTCLASS_PLAYER</Class>
		<TraitPrereq>TRAIT_CORRUPTIONIST_ARCHETYPE</TraitPrereq>
	</Entry>
	<Entry>
		<zType>SUBJECT_PLAYER_ARTIST</zType>
		<Class>SUBJECTCLASS_PLAYER</Class>
		<TraitPrereq>TRAIT_ARTIST_ARCHETYPE</TraitPrereq>
	</Entry>
	<Entry>
		<zType>SUBJECT_PLAYER_MERCHANT</zType>
		<Class>SUBJECTCLASS_PLAYER</Class>
		<TraitPrereq>TRAIT_MERCHANT_ARCHETYPE</TraitPrereq>
	</Entry>
	<Entry>
		<zType>SUBJECT_PLAYER_CHAMPION</zType>
		<Class>SUBJECTCLASS_PLAYER</Class>
		<TraitPrereq>TRAIT_CHAMPION_ARCHETYPE</TraitPrereq>
		<aiMinRating>
			<Pair>
				<zIndex>RATING_COURAGE</zIndex>
				<iValue>2</iValue>
			</Pair>
			<Pair>
				<zIndex>RATING_CHARISMA</zIndex>
				<iValue>1</iValue>
			</Pair>
		</aiMinRating>
	</Entry>
	<Entry>
		<zType>SUBJECT_SKYEXPLORER</zType>
		<Class>SUBJECTCLASS_CHARACTER</Class>
		<TraitPrereq>TRAIT_SKYEXPLORER_ARCHETYPE</TraitPrereq>
	</Entry>
		<Entry>
		<zType>SUBJECT_CORRUPTIONIST</zType>
		<Class>SUBJECTCLASS_CHARACTER</Class>
		<TraitPrereq>TRAIT_CORRUPTIONIST_ARCHETYPE</TraitPrereq>
	</Entry>
	<Entry>
		<zType>SUBJECT_ARTIST</zType>
		<Class>SUBJECTCLASS_CHARACTER</Class>
		<TraitPrereq>TRAIT_ARTIST_ARCHETYPE</TraitPrereq>
	</Entry>
	<Entry>
		<zType>SUBJECT_MERCHANT</zType>
		<Class>SUBJECTCLASS_CHARACTER</Class>
		<TraitPrereq>TRAIT_MERCHANT_ARCHETYPE</TraitPrereq>
	</Entry>
	<Entry>
		<zType>SUBJECT_CHAMPION</zType>
		<Class>SUBJECTCLASS_CHARACTER</Class>
		<TraitPrereq>TRAIT_CHAMPION_ARCHETYPE</TraitPrereq>
	</Entry>
	<Entry>
		<zType>SUBJECT_GREAT_SKYEXPLORER</zType>
		<Class>SUBJECTCLASS_CHARACTER</Class>
		<CourtierPrereq>COURTIER_GREAT_SKYEXPLORER</CourtierPrereq>
	</Entry>
	<Entry>
		<zType>SUBJECT_FAMOUS_PERSON</zType>
		<Class>SUBJECTCLASS_CHARACTER</Class>
		<TraitPrereq>TRAIT_FAMOUS_PERSON</TraitPrereq>
	</Entry>
	<Entry>
		<zType>SUBJECT_LEADER_SKYEXPLORER</zType>
		<zName>Sky Explorer Leader</zName>
		<Class>SUBJECTCLASS_CHARACTER</Class>
		<TraitPrereq>TRAIT_SKYEXPLORER_ARCHETYPE</TraitPrereq>
		<bLeader>1</bLeader>
	</Entry>
	<Entry>
		<zType>SUBJECT_LEADER_CORRUPTIONIST</zType>
		<zName>Corruptionist Leader</zName>
		<Class>SUBJECTCLASS_CHARACTER</Class>
		<TraitPrereq>TRAIT_CORRUPTIONIST_ARCHETYPE</TraitPrereq>
		<bLeader>1</bLeader>
	</Entry>
	<Entry>
		<zType>SUBJECT_LEADER_ARTIST</zType>
		<zName>Artist Leader</zName>
		<Class>SUBJECTCLASS_CHARACTER</Class>
		<TraitPrereq>TRAIT_ARTIST_ARCHETYPE</TraitPrereq>
		<bLeader>1</bLeader>
	</Entry>
	<Entry>
		<zType>SUBJECT_LEADER_MERCHANT</zType>
		<zName>Merchant Leader</zName>
		<Class>SUBJECTCLASS_CHARACTER</Class>
		<TraitPrereq>TRAIT_MERCHANT_ARCHETYPE</TraitPrereq>
		<bLeader>1</bLeader>
	</Entry>
	<Entry>
		<zType>SUBJECT_LEADER_CHAMPION</zType>
		<zName>CHampion Leader</zName>
		<Class>SUBJECTCLASS_CHARACTER</Class>
		<TraitPrereq>TRAIT_CHAMPION_ARCHETYPE</TraitPrereq>
		<bLeader>1</bLeader>
	</Entry>
	<Entry>
		<zType>SUBJECT_ALCIBIADES</zType>
		<Class>SUBJECTCLASS_CHARACTER</Class>
		<Character>CHARACTER_ALCIBIADES</Character>
	</Entry>
	<Entry>
		<zType>SUBJECT_POLYBIOS</zType>
		<Class>SUBJECTCLASS_CHARACTER</Class>
		<Character>CHARACTER_POLYBIOS</Character>
	</Entry>
	<Entry>
		<zType>SUBJECT_ANTIPHON</zType>
		<Class>SUBJECTCLASS_CHARACTER</Class>
		<Character>CHARACTER_ANTIPHON</Character>
	</Entry>
	<Entry>
		<zType>SUBJECT_DOROTHEOS</zType>
		<Class>SUBJECTCLASS_CHARACTER</Class>
		<Character>CHARACTER_DOROTHEOS</Character>
	</Entry>
	<Entry>
		<zType>SUBJECT_DEMOSTHENSES</zType>
		<Class>SUBJECTCLASS_CHARACTER</Class>
		<Character>CHARACTER_DEMOSTHENSES</Character>
	</Entry>
	<Entry>
		<zType>SUBJECT_TRIBONIANUS</zType>
		<Class>SUBJECTCLASS_CHARACTER</Class>
		<Character>CHARACTER_TRIBONIANUS</Character>
	</Entry>
	<Entry>
		<zType>SUBJECT_ANTONIUS</zType>
		<Class>SUBJECTCLASS_CHARACTER</Class>
		<Character>CHARACTER_ANTONIUS</Character>
	</Entry>
	<Entry>
		<zType>SUBJECT_BRUTUS</zType>
		<Class>SUBJECTCLASS_CHARACTER</Class>
		<Character>CHARACTER_BRUTUS</Character>
	</Entry>
	<Entry>
		<zType>SUBJECT_CAMILLUS</zType>
		<Class>SUBJECTCLASS_CHARACTER</Class>
		<Character>CHARACTER_CAMILLUS</Character>
	</Entry>
	<Entry>
		<zType>SUBJECT_CATILINA</zType>
		<Class>SUBJECTCLASS_CHARACTER</Class>
		<Character>CHARACTER_CATILINA</Character>
	</Entry>
	<Entry>
		<zType>SUBJECT_CATULLUS</zType>
		<Class>SUBJECTCLASS_CHARACTER</Class>
		<Character>CHARACTER_CATULLUS</Character>
	</Entry>
	<Entry>
		<zType>SUBJECT_BATIATUS</zType>
		<Class>SUBJECTCLASS_CHARACTER</Class>
		<Character>CHARACTER_BATIATUS</Character>
	</Entry>
	<Entry>
		<zType>SUBJECT_IDDIN_MARDUK</zType>
		<Class>SUBJECTCLASS_CHARACTER</Class>
		<Character>CHARACTER_IDDIN_MARDUK</Character>
	</Entry>
	<Entry>
		<zType>SUBJECT_EUMACHIA</zType>
		<Class>SUBJECTCLASS_CHARACTER</Class>
		<Character>CHARACTER_EUMACHIA</Character>
	</Entry>
	<Entry>
		<zType>SUBJECT_CICERO</zType>
		<Class>SUBJECTCLASS_CHARACTER</Class>
		<Character>CHARACTER_CICERO</Character>
	</Entry>
	<Entry>
		<zType>SUBJECT_ANKH_AF_NA_KHONSU</zType>
		<Class>SUBJECTCLASS_CHARACTER</Class>
		<Character>CHARACTER_ANKH_AF_NA_KHONSU</Character>
	</Entry>
	<Entry>
		<zType>SUBJECT_ARISTOMACHOS</zType>
		<Class>SUBJECTCLASS_CHARACTER</Class>
		<Character>CHARACTER_ARISTOMACHOS</Character>
	</Entry>
	<Entry>
		<zType>SUBJECT_MNESTER</zType>
		<Class>SUBJECTCLASS_CHARACTER</Class>
		<Character>CHARACTER_MNESTER</Character>
	</Entry>
	<Entry>
		<zType>SUBJECT_TUTOR_GREECE_ARCHIMEDES</zType>
		<Class>SUBJECTCLASS_CHARACTER</Class>
		<Character>CHARACTER_TUTOR_GREECE_ARCHIMEDES</Character>
	</Entry>
</Root>
